cdataclass/__init__.py
cdataclass/core.py
cdataclass/metadata.py
cdataclass/py.typed
cdataclass/type.py
cdataclass-0.1.2.dist-info/LICENSE
cdataclass-0.1.2.dist-info/METADATA
cdataclass-0.1.2.dist-info/WHEEL
cdataclass-0.1.2.dist-info/top_level.txt
cdataclass-0.1.2.dist-info/RECORD
