Metadata-Version: 2.1
Name: cdataclass
Version: 0.1.2
Summary: Integration of ctypes and dataclasses
Home-page: https://github.com/hajoks/cdata
Author: hajoks
Author-email: syari4369@gmail.com
License: MIT
Download-URL: https://github.com/hajoks/cdata
Keywords: dataclasses ctypes
Platform: UNKNOWN
Requires-Python: >=3.6
License-File: LICENSE
Requires-Dist: dataclasses ; python_version == "3.6"
Provides-Extra: dev
